Metadata-Version: 2.1
Name: anikimiapi
Version: 0.1.4
Summary: A Simple, LightWeight, Statically-Typed Python3 API wrapper for GogoAnime
Home-page: https://github.com/BaraniARR/anikimiapi
Author: BaraniARR
Author-email: baranikumar2003@outlook.com
License: LGPLv3+
Download-URL: https://github.com/BaraniARR/anikimiapi/releases/tag/v0.0.1-beta
Keywords: anime,gogoanime,download,sub,dub
Platform: UNKNOWN
Classifier: Development Status :: 4 - Beta
Classifier: Intended Audience :: Developers
Classifier: Topic :: Internet
Classifier: License :: OSI Approved :: GNU Lesser General Public License v3 or later (LGPLv3+)
Classifier: Programming Language :: Python :: 3.6
Classifier: Programming Language :: Python :: 3.7
Classifier: Programming Language :: Python :: 3.8
Classifier: Programming Language :: Python :: 3.9
Classifier: Programming Language :: Python :: 3.10
